perisim/__init__.py
perisim/perisim.py
perisim-0.45.dist-info/METADATA
perisim-0.45.dist-info/RECORD
perisim-0.45.dist-info/WHEEL
perisim-0.45.dist-info/top_level.txt
