Metadata-Version: 2.1
Name: perisim
Version: 0.45
Summary: A package for simulating peristaltic tables
Home-page: https://github.com/stokesresearchgroup/perisim
Author: Ross M. McKenzie
Author-email: r.m.mckenzie@ed.ac.uk
License: MIT
Platform: UNKNOWN
Requires-Dist: torch
